Metadata-Version: 2.1
Name: uaDevice
Version: 2.0.1
Summary: User Agent parser, More accurate
Home-page: https://github.com/kaivean/python-ua-device
Author: kaivean
Author-email: kaivean@outlook.com
License: MIT Licence
Keywords: ua,user-agent,User Agent,parser,device,os,browser,engine,data analysis,china,中国,国内
Platform: any
